wolvr/__about__.py
wolvr/__init__.py
wolvr/unit_conversion.py
wolvr/datasets/__init__.py
wolvr/datasets/_datasets.py
wolvr/datasets/public/README.txt
wolvr/datasets/public/SMS_Spam_Collection/SMSSpamCollection.tsv
wolvr/datasets/public/SMS_Spam_Collection/readme
wolvr/datasets/public/Social_Network_Ads/Social_Network_Ads.csv
wolvr/datasets/public/nltk_data/corpora/wordnet/LICENSE
wolvr/datasets/public/nltk_data/corpora/wordnet/README
wolvr/datasets/public/nltk_data/corpora/wordnet/adj.exc
wolvr/datasets/public/nltk_data/corpora/wordnet/adv.exc
wolvr/datasets/public/nltk_data/corpora/wordnet/citation.bib
wolvr/datasets/public/nltk_data/corpora/wordnet/cntlist.rev
wolvr/datasets/public/nltk_data/corpora/wordnet/data.adj
wolvr/datasets/public/nltk_data/corpora/wordnet/data.adv
wolvr/datasets/public/nltk_data/corpora/wordnet/data.noun
wolvr/datasets/public/nltk_data/corpora/wordnet/data.verb
wolvr/datasets/public/nltk_data/corpora/wordnet/index.adj
wolvr/datasets/public/nltk_data/corpora/wordnet/index.adv
wolvr/datasets/public/nltk_data/corpora/wordnet/index.noun
wolvr/datasets/public/nltk_data/corpora/wordnet/index.sense
wolvr/datasets/public/nltk_data/corpora/wordnet/index.verb
wolvr/datasets/public/nltk_data/corpora/wordnet/lexnames
wolvr/datasets/public/nltk_data/corpora/wordnet/noun.exc
wolvr/datasets/public/nltk_data/corpora/wordnet/verb.exc
wolvr/datasets/public/nltk_data/tokenizers/punkt/README
wolvr/datasets/public/nltk_data/tokenizers/punkt/czech.pickle
wolvr/datasets/public/nltk_data/tokenizers/punkt/danish.pickle
wolvr/datasets/public/nltk_data/tokenizers/punkt/dutch.pickle
wolvr/datasets/public/nltk_data/tokenizers/punkt/english.pickle
wolvr/datasets/public/nltk_data/tokenizers/punkt/estonian.pickle
wolvr/datasets/public/nltk_data/tokenizers/punkt/finnish.pickle
wolvr/datasets/public/nltk_data/tokenizers/punkt/french.pickle
wolvr/datasets/public/nltk_data/tokenizers/punkt/german.pickle
wolvr/datasets/public/nltk_data/tokenizers/punkt/greek.pickle
wolvr-0.0.7.dist-info/LICENSE
wolvr-0.0.7.dist-info/METADATA
wolvr-0.0.7.dist-info/WHEEL
wolvr-0.0.7.dist-info/top_level.txt
wolvr-0.0.7.dist-info/RECORD
