Metadata-Version: 2.1
Name: wolvr
Version: 0.0.7
Summary: Utility Belt for Machine Learning
Home-page: https://github.com/tombresee/wolvr
Author: Tom Bresee
Author-email: tbresee@umich.edu
License: BSD 3-Clause
Platform: UNKNOWN
Classifier: Topic :: Scientific/Engineering
Classifier: Programming Language :: Python :: 3
Classifier: Programming Language :: Python :: 3.6
Classifier: Programming Language :: Python :: 3.7
Classifier: Programming Language :: Python :: 3.8
Classifier: License :: OSI Approved :: BSD License
Classifier: Operating System :: OS Independent
Requires-Python: >=3.6
Requires-Dist: scikit-learn (>=0.23.2)
Requires-Dist: numpy (>=1.19.2)
Requires-Dist: seaborn (>=0.11.0)
Requires-Dist: matplotlib (>=3.3.2)
Requires-Dist: pandas (>=1.1.2)
Requires-Dist: textblob (>=0.15.3)
Requires-Dist: nltk (>=3.5)
